odoo/addons/account_einvoice_generate/README.rst
odoo/addons/account_einvoice_generate/__init__.py
odoo/addons/account_einvoice_generate/__manifest__.py
odoo/addons/account_einvoice_generate/post_install.py
odoo/addons/account_einvoice_generate/i18n/account_e-invoice_generate.pot
odoo/addons/account_einvoice_generate/i18n/account_einvoice_generate.pot
odoo/addons/account_einvoice_generate/i18n/es.po
odoo/addons/account_einvoice_generate/i18n/fr.po
odoo/addons/account_einvoice_generate/i18n/hr.po
odoo/addons/account_einvoice_generate/i18n/it.po
odoo/addons/account_einvoice_generate/models/__init__.py
odoo/addons/account_einvoice_generate/models/account_move.py
odoo/addons/account_einvoice_generate/models/res_company.py
odoo/addons/account_einvoice_generate/readme/CONFIGURE.md
odoo/addons/account_einvoice_generate/readme/CONTRIBUTORS.md
odoo/addons/account_einvoice_generate/readme/DESCRIPTION.md
odoo/addons/account_einvoice_generate/readme/INSTALL.md
odoo/addons/account_einvoice_generate/static/description/icon.png
odoo/addons/account_einvoice_generate/static/description/index.html
odoo/addons/account_einvoice_generate/tests/__init__.py
odoo/addons/account_einvoice_generate/tests/test_einvoice_generate.py
odoo/addons/account_einvoice_generate/views/res_config_settings.xml
odoo/addons/account_einvoice_generate/wizards/__init__.py
odoo/addons/account_einvoice_generate/wizards/res_config_settings.py
odoo_addon_account_einvoice_generate-18.0.1.0.0.5.dist-info/METADATA
odoo_addon_account_einvoice_generate-18.0.1.0.0.5.dist-info/WHEEL
odoo_addon_account_einvoice_generate-18.0.1.0.0.5.dist-info/top_level.txt
odoo_addon_account_einvoice_generate-18.0.1.0.0.5.dist-info/RECORD
