Metadata-Version: 2.1
Name: odoo-addon-account_einvoice_generate
Version: 18.0.1.0.0.5
Requires-Python: >=3.10
Requires-Dist: odoo==18.0.*
Summary: Technical module to generate PDF invoices with embedded XML file
Home-page: https://github.com/OCA/edi
License: AGPL-3
Author: Akretion,Onestein,Odoo Community Association (OCA)
Author-email: support@odoo-community.org
Classifier: Programming Language :: Python
Classifier: Framework :: Odoo
Classifier: Framework :: Odoo :: 18.0
Classifier: License :: OSI Approved :: GNU Affero General Public License v3
